pypg_stream_consumer/__init__.py
pypg_stream_consumer/consumer.py
pypg_stream_consumer/filters.py
pypg_stream_consumer/models.py
pypg_stream_consumer/serializers/__init__.py
pypg_stream_consumer/serializers/factory.py
pypg_stream_consumer/serializers/impl/__init__.py
pypg_stream_consumer/serializers/impl/class_serializer.py
pypg_stream_consumer/serializers/serializer_abc.py
pypg_stream_consumer-0.0.6.dist-info/METADATA
pypg_stream_consumer-0.0.6.dist-info/WHEEL
pypg_stream_consumer-0.0.6.dist-info/RECORD
